{"assets/fonts/CustomIcons.ttf":["assets/fonts/CustomIcons.ttf"],"assets/fonts/agustina.otf":["assets/fonts/agustina.otf"],"assets/gif/wave_hand.gif":["assets/gif/wave_hand.gif"],"assets/images/.DS_Store":["assets/images/.DS_Store"],"assets/images/404.png":["assets/images/404.png"],"assets/images/android.png":["assets/images/android.png"],"assets/images/androidstudio.svg":["assets/images/androidstudio.svg"],"assets/images/app_icon_dark.png":["assets/images/app_icon_dark.png"],"assets/images/app_icon_light.png":["assets/images/app_icon_light.png"],"assets/images/ios.png":["assets/images/ios.png"],"assets/images/mac.png":["assets/images/mac.png"],"assets/images/postman.svg":["assets/images/postman.svg"],"assets/images/roshan.png":["assets/images/roshan.png"],"assets/images/web.png":["assets/images/web.png"],"assets/images/windows.png":["assets/images/windows.png"],"assets/images/xcode.svg":["assets/images/xcode.svg"],"assets/svg/.DS_Store":["assets/svg/.DS_Store"],"assets/svg/css.svg":["assets/svg/css.svg"],"assets/svg/dart.svg":["assets/svg/dart.svg"],"assets/svg/figma.svg":["assets/svg/figma.svg"],"assets/svg/firebase.svg":["assets/svg/firebase.svg"],"assets/svg/flutter.svg":["assets/svg/flutter.svg"],"assets/svg/git.svg":["assets/svg/git.svg"],"assets/svg/html.svg":["assets/svg/html.svg"],"assets/svg/java.svg":["assets/svg/java.svg"],"assets/svg/javascript.svg":["assets/svg/javascript.svg"],"assets/svg/menu.svg":["assets/svg/menu.svg"],"assets/svg/mysql.svg":["assets/svg/mysql.svg"],"assets/svg/photoshop.svg":["assets/svg/photoshop.svg"],"assets/svg/python.svg":["assets/svg/python.svg"],"assets/svg/vscode.svg":["assets/svg/vscode.svg"],"assets/svg/xd.svg":["assets/svg/xd.svg"]}